{
    "$schema": "https://schema.management.azure.com/schemas/2015-01-01/deploymentParameters.json#",
    "contentVersion": "1.0.0.0",
    "parameters": {
        "appservicename": {
            "value": "cocacola-serviceplan-secondary"
        },
        "webappnames": {
            "value": ["cocacola-webapp-prod-secondary"]
        },
        "environment" : {
            "value": "prod"
        },
        "location": {
            "value": "westeurope"
        },
        "costcenter": {
            "value": "cocacola"
        },
        "owner" : {
            "value": "DASH"
         },
        "appinsight" : {
            "value": "no"
        },
        "workersize": {
            "value": "0"
        },
        "webappsku": {
            "value": "Standard"
        }
    }
}
